healthchecks_manager/__init__.py
healthchecks_manager/healthchecks_api_wrapper.py
healthchecks_manager/manager.py
tests/__init__.py
tests/test_ahealthchecks.py
healthchecks_manager-0.1.4.dist-info/METADATA
healthchecks_manager-0.1.4.dist-info/WHEEL
healthchecks_manager-0.1.4.dist-info/top_level.txt
healthchecks_manager-0.1.4.dist-info/RECORD
