Metadata-Version: 2.1
Name: healthchecks-manager
Version: 0.1.4
Summary: Library for automatic registration and pinging of https://healthchecks.io/ healthchecks.
Home-page: https://github.com/15five/healthchecks-manager
Author: Caleb Sparks
Author-email: caleb@15five.com
License: MIT
Keywords: healthchecks healthchecks.io registration creation
Platform: UNKNOWN
Classifier: Development Status :: 2 - Pre-Alpha
Classifier: Intended Audience :: Developers
Classifier: Intended Audience :: System Administrators
Classifier: License :: OSI Approved :: MIT License
Classifier: Operating System :: OS Independent
Classifier: Natural Language :: English
Classifier: Topic :: Software Development :: Libraries :: Python Modules
Classifier: Topic :: Internet
Classifier: Programming Language :: Python :: 3
Classifier: Programming Language :: Python :: 3.6
Classifier: Programming Language :: Python :: 3.7
Classifier: Programming Language :: Python :: 3.8
Requires-Python: >=3
Requires-Dist: requests (==2.20.1)
